ReadIM/__init__.py
ReadIM/_core.cp37-win_amd64.pyd
ReadIM/core.py
ReadIM/core_wrap.cxx
ReadIM/extra.py
ReadIM/sample_files/1camera.im7
ReadIM/sample_files/2C.VC7
ReadIM/sample_files/2cameras.im7
ReadIM/sample_files/3C.VC7
ReadIM/src/ReadIM7.cpp
ReadIM/src/ReadIM7.h
ReadIM/src/ReadIMX.cpp
ReadIM/src/ReadIMX.h
ReadIM/src/swigExtras.cpp
ReadIM/src/swigExtras.h
ReadIM/src/zlib/Makefile
ReadIM/src/zlib/adler32.c
ReadIM/src/zlib/compress.c
ReadIM/src/zlib/deflate.c
ReadIM/src/zlib/deflate.h
ReadIM/src/zlib/infblock.c
ReadIM/src/zlib/infblock.h
ReadIM/src/zlib/infcodes.c
ReadIM/src/zlib/infcodes.h
ReadIM/src/zlib/inffast.c
ReadIM/src/zlib/inffast.h
ReadIM/src/zlib/inffixed.h
ReadIM/src/zlib/inflate.c
ReadIM/src/zlib/inftrees.c
ReadIM/src/zlib/inftrees.h
ReadIM/src/zlib/infutil.c
ReadIM/src/zlib/infutil.h
ReadIM/src/zlib/trees.c
ReadIM/src/zlib/trees.h
ReadIM/src/zlib/uncompr.c
ReadIM/src/zlib/zconf.h
ReadIM/src/zlib/zlib.h
ReadIM/src/zlib/zutil.c
ReadIM/src/zlib/zutil.h
ReadIM-0.8.4.dist-info/LICENSE
ReadIM-0.8.4.dist-info/METADATA
ReadIM-0.8.4.dist-info/WHEEL
ReadIM-0.8.4.dist-info/top_level.txt
ReadIM-0.8.4.dist-info/RECORD
