Metadata-Version: 2.1
Name: ReadIM
Version: 0.8.4
Summary: Read and write native DaVis images and vectors filetypes VC7 and IM7
Home-page: https://bitbucket.org/fleming79/readim
License: MIT
Keywords: IM7 VC7 DaVis LaVision FileIO PIV
Platform: UNKNOWN
Classifier: Development Status :: 4 - Beta
Classifier: Intended Audience :: Developers
Classifier: Topic :: Software Development :: Build Tools
Classifier: License :: OSI Approved :: MIT License
Classifier: Programming Language :: Python :: 3.4
Classifier: Programming Language :: Python :: 3.5
Classifier: Programming Language :: Python :: 3.6
Classifier: Programming Language :: Python :: 3.7
Classifier: Programming Language :: Python :: 3.8
